paraqeet/__init__.py
paraqeet/exceptions.py
paraqeet/file_logger.py
paraqeet/logger.py
paraqeet/optimisable.py
paraqeet/optimisation_map.py
paraqeet/quantity.py
paraqeet/measurement/__init__.py
paraqeet/measurement/goat_over_grape.py
paraqeet/measurement/makhlin_functional.py
paraqeet/measurement/measurement.py
paraqeet/measurement/mixed_state_transfer_fidelity.py
paraqeet/measurement/rabi_experiment.py
paraqeet/measurement/state_transfer_fidelity.py
paraqeet/measurement/unitary_fidelity.py
paraqeet/measurement/weighted_sum_goal.py
paraqeet/model/__init__.py
paraqeet/model/closed_system.py
paraqeet/model/composite_hamiltonian.py
paraqeet/model/coupling.py
paraqeet/model/custom_hamiltonian.py
paraqeet/model/drive.py
paraqeet/model/drive_operator.py
paraqeet/model/equation_of_motion.py
paraqeet/model/hamiltonian.py
paraqeet/model/open_system.py
paraqeet/model/qubit.py
paraqeet/model/resonator.py
paraqeet/model/rotating_frame_coupling.py
paraqeet/model/rotating_frame_drive.py
paraqeet/model/transmon.py
paraqeet/optimisers/bayesian_optimiser.py
paraqeet/optimisers/cmaes_optimiser.py
paraqeet/optimisers/optimiser.py
paraqeet/optimisers/scipy_optimiser.py
paraqeet/optimisers/scipy_optimiser_gradient.py
paraqeet/propagation/__init__.py
paraqeet/propagation/euler.py
paraqeet/propagation/propagation.py
paraqeet/propagation/runge_kutta.py
paraqeet/propagation/scipy_expm.py
paraqeet/propagation/scipy_expm_goat.py
paraqeet/propagation/scipy_expm_grape.py
paraqeet/propagation/state_propagation.py
paraqeet/propagation/vern7.py
paraqeet/propagation/vern7_grape.py
paraqeet/serialisation/json_file_serialiser.py
paraqeet/serialisation/serialiser.py
paraqeet/signal/__init__.py
paraqeet/signal/envelopes.py
paraqeet/signal/generator.py
paraqeet/signal/iq_mixer.py
paraqeet/signal/pwc_generator.py
paraqeet/signal/waveform.py
paraqeet-0.9.1.dist-info/licenses/LICENSE
paraqeet-0.9.1.dist-info/METADATA
paraqeet-0.9.1.dist-info/WHEEL
paraqeet-0.9.1.dist-info/top_level.txt
paraqeet-0.9.1.dist-info/RECORD
