Metadata-Version: 2.4
Name: paraqeet
Version: 0.9.1
Summary: Toolset for control, calibration and characterization of physical systems
Author: PGI-12
Project-URL: Homepage, https://jugit.fz-juelich.de/pgi-12-external/qfc/paraqeet
Project-URL: Bug Reports, https://jugit.fz-juelich.de/pgi-12-external/qfc/paraqeet/-/issues
Project-URL: Source, https://jugit.fz-juelich.de/pgi-12-external/qfc/paraqeet
Classifier: Development Status :: 4 - Beta
Classifier: License :: OSI Approved :: Apache Software License
Classifier: Intended Audience :: Science/Research
Classifier: Operating System :: MacOS
Classifier: Operating System :: Microsoft :: Windows :: Windows 10
Classifier: Operating System :: Unix
Classifier: Programming Language :: Python :: 3.12
Classifier: Topic :: Scientific/Engineering :: Artificial Intelligence
Classifier: Topic :: Scientific/Engineering :: Physics
Requires-Python: >=3.12
License-File: LICENSE
Requires-Dist: numpy>=2.3.0
Requires-Dist: scipy>=1.15.3
Requires-Dist: jax>=0.6.1
Requires-Dist: jaxlib>=0.6.1
Requires-Dist: bayesian-optimization>=2.0.4
Requires-Dist: cma>=4.2.0
Provides-Extra: dev
Requires-Dist: pytest>=7.2.0; extra == "dev"
Requires-Dist: pre-commit>=4.2.0; extra == "dev"
Requires-Dist: ruff>=0.11.13; extra == "dev"
Provides-Extra: test
Requires-Dist: pytest>=7.2.0; extra == "test"
Provides-Extra: testnb
Requires-Dist: pytest>=7.2.0; extra == "testnb"
Requires-Dist: matplotlib>=3.10.0; extra == "testnb"
Provides-Extra: gpu
Requires-Dist: jax[cuda12]>=0.4.20; extra == "gpu"
Dynamic: license-file
